[{"title":"Notebook","description":"Notebook intel celeron","code":"utf-8","price":100100,"status":true,"stock":29,"category":"tecnologia","id":"T"},{"title":"Mochila","description":"Mochila Everlast Original","code":"utf-8","price":1000,"status":true,"stock":9,"category":"accesorio","id":"C"},{"title":"celular","description":"Samsung Galaxy","code":"utf-8","price":53000,"status":true,"stock":4,"category":"tecnologia","id":"9"},{"title":"Pad Mouse","description":"Map Of Lord Of The Rings","code":"utf-8","price":4200,"status":true,"stock":1,"category":"accesorios","id":"B"},{"title":"Anillos De Encuadernacion","description":"Anillos De Encuadernacion De Hojas","code":"utf-8","price":900,"status":true,"stock":7,"category":"libreria","id":"u"},{"title":"Aspiradora","description":"Philco Ciclonica","code":"utf-8","price":9500,"status":true,"stock":2,"category":"electrodomestico","id":"s"},{"title":"Heladera","description":"no frost Philco","code":"utf-8","price":350000,"status":true,"stock":5,"category":"electrodomestico","id":"3"},{"title":"Gafas","description":"Gafas Aviador Lentes Unisex Clásicos Tendencia 2022","code":"utf-8","price":1400,"status":true,"stock":3,"category":"accesorio","id":"T"},{"title":"Auriculares","description":"Auriculares Beats Solo","code":"utf-8","price":63000,"status":true,"stock":8,"category":"accesorio electrodomestico","id":"c"}]